MANIFEST.in
README.md
setup.cfg
setup.py
git_vendor.egg-info/PKG-INFO
git_vendor.egg-info/SOURCES.txt
git_vendor.egg-info/dependency_links.txt
git_vendor.egg-info/entry_points.txt
git_vendor.egg-info/not-zip-safe
git_vendor.egg-info/pbr.json
git_vendor.egg-info/requires.txt
git_vendor.egg-info/top_level.txt
gitvendor/__init__.py
gitvendor/cli.py
gitvendor/gitvendor.py
gitvendor/helpers.py
gitvendor/init.py
gitvendor/sync.py
gitvendor/version.py
gitvendor/template/vendor-rc