Metadata-Version: 1.1
Name: git-vendor
Version: 0.0.3
Summary: Vendor tagged releases from git to $VCS
Home-page: http://github.com/chuckbutler/git-vendor
Author: Charles Butler
Author-email: charles.butler@ubuntu.com
License: MIT License
Download-URL: https://github.com/chuckbutler/git-vendor/releases/
Keywords: git,vendor
Platform: UNKNOWN
Classifier: Development Status :: 3 - Alpha
Classifier: License :: OSI Approved :: MIT License
Classifier: Environment :: Console
Classifier: Topic :: Software Development
